{
  "$schema": "https://developer.microsoft.com/json-schemas/fabric/item/report/definition/visualContainer/2.0.0/schema.json",
  "name": "1cb52e84f5fe75b30684",
  "position": {
    "x": 128.10264635124292,
    "y": 0,
    "z": 10000,
    "height": 39.416198877305533,
    "width": 171.62469927826785,
    "tabOrder": 0
  },
  "visual": {
    "visualType": "slicer",
    "query": {
      "queryState": {
        "Values": {
          "projections": [
            {
              "field": {
                "Column": {
                  "Expression": {
                    "SourceRef": {
                      "Entity": "Date"
                    }
                  },
                  "Property": "Year"
                }
              },
              "queryRef": "Date.Year",
              "nativeQueryRef": "Year",
              "active": true
            },
            {
              "field": {
                "Column": {
                  "Expression": {
                    "SourceRef": {
                      "Entity": "Date"
                    }
                  },
                  "Property": "Month"
                }
              },
              "queryRef": "Date.Month",
              "nativeQueryRef": "Month",
              "active": false
            }
          ]
        }
      }
    },
    "expansionStates": [
      {
        "roles": [
          "Values"
        ],
        "levels": [
          {
            "queryRefs": [
              "Date.Year"
            ],
            "isCollapsed": true,
            "identityKeys": [
              {
                "Column": {
                  "Expression": {
                    "SourceRef": {
                      "Entity": "Date"
                    }
                  },
                  "Property": "Year"
                }
              }
            ],
            "isPinned": true
          },
          {
            "queryRefs": [
              "Date.Month"
            ],
            "isCollapsed": true,
            "isPinned": true
          }
        ],
        "root": {}
      }
    ],
    "objects": {
      "data": [
        {
          "properties": {
            "mode": {
              "expr": {
                "Literal": {
                  "Value": "'Dropdown'"
                }
              }
            }
          }
        }
      ],
      "header": [
        {
          "properties": {
            "textSize": {
              "expr": {
                "Literal": {
                  "Value": "10D"
                }
              }
            },
            "fontFamily": {
              "expr": {
                "Literal": {
                  "Value": "'Cambria'"
                }
              }
            },
            "text": {
              "expr": {
                "Literal": {
                  "Value": "'Select Year & Month'"
                }
              }
            },
            "show": {
              "expr": {
                "Literal": {
                  "Value": "false"
                }
              }
            }
          }
        }
      ],
      "general": [
        {
          "properties": {}
        }
      ],
      "items": [
        {
          "properties": {
            "expandCollapseToggleType": {
              "expr": {
                "Literal": {
                  "Value": "2D"
                }
              }
            },
            "padding": {
              "expr": {
                "Literal": {
                  "Value": "0D"
                }
              }
            },
            "fontColor": {
              "solid": {
                "color": {
                  "expr": {
                    "ThemeDataColor": {
                      "ColorId": 0,
                      "Percent": 0
                    }
                  }
                }
              }
            },
            "background": {
              "solid": {
                "color": {
                  "expr": {
                    "ThemeDataColor": {
                      "ColorId": 0,
                      "Percent": -0.6
                    }
                  }
                }
              }
            }
          }
        }
      ]
    },
    "visualContainerObjects": {
      "background": [
        {
          "properties": {
            "show": {
              "expr": {
                "Literal": {
                  "Value": "false"
                }
              }
            }
          }
        }
      ]
    },
    "drillFilterOtherVisuals": true
  },
  "parentGroupName": "691313ef230bc1086e42"
}